yzm_mcp_txt_from_url/__init__.py
yzm_mcp_txt_from_url-0.1.0.dist-info/WHEEL
yzm_mcp_txt_from_url-0.1.0.dist-info/entry_points.txt
yzm_mcp_txt_from_url-0.1.0.dist-info/METADATA
yzm_mcp_txt_from_url-0.1.0.dist-info/RECORD
